torchshape/__init__.py
torchshape/shape_calculator.py
torchshape-0.0.8.dist-info/LICENSE
torchshape-0.0.8.dist-info/METADATA
torchshape-0.0.8.dist-info/WHEEL
torchshape-0.0.8.dist-info/top_level.txt
torchshape-0.0.8.dist-info/RECORD
