Metadata-Version: 2.1
Name: torchshape
Version: 0.0.8
Summary: Calculates the output shape of Pytorch operations
Home-page: https://github.com/yuezuegu/torchshape
Author: Ahmer Caner Yuzuguler
Author-email: ahmet.yuzuguler@epfl.ch
License: UNKNOWN
Project-URL: Bug Tracker, https://github.com/yuezuegu/torchshape/issues
Platform: UNKNOWN
Classifier: Programming Language :: Python :: 3
Classifier: License :: OSI Approved :: MIT License
Classifier: Operating System :: OS Independent
Requires-Python: >=3.6
License-File: LICENSE
